XiaoMing/__init__.py
XiaoMing-0.0.2.dist-info/LICENSE
XiaoMing-0.0.2.dist-info/METADATA
XiaoMing-0.0.2.dist-info/WHEEL
XiaoMing-0.0.2.dist-info/top_level.txt
XiaoMing-0.0.2.dist-info/RECORD
