Metadata-Version: 2.1
Name: XiaoMing
Version: 0.0.2
Summary: 一个自己的库
Home-page: https://github.com/XiaoMing5442/XiaoMing
Author: XiaoMing5442
Author-email: XiaoMing5442@outlook.com
Classifier: Programming Language :: Python :: 3
Requires-Python: >=3.10
License-File: LICENSE
Requires-Dist: shutils
